my_pypi_custom_package/__init__.py
my_pypi_custom_package/basic/__init__.py
my_pypi_custom_package/basic/hello_world.py
my_pypi_custom_package/basic/hello_world_2.py
my_pypi_custom_package/basic/algebra/__init__.py
my_pypi_custom_package/basic/algebra/addition.py
my_pypi_custom_package/basic/algebra/subraction.py
my_pypi_custom_package/basic/custom_utils/__init__.py
my_pypi_custom_package/basic/custom_utils/today_date.py
my_pypi_custom_package/sorting/__init__.py
my_pypi_custom_package/sorting/sorted_list.py
my_pypi_custom_package_dev-0.0.30.dist-info/METADATA
my_pypi_custom_package_dev-0.0.30.dist-info/WHEEL
my_pypi_custom_package_dev-0.0.30.dist-info/top_level.txt
my_pypi_custom_package_dev-0.0.30.dist-info/RECORD
